{
  "project_info": {
    "project_number": "936578715641",
    "project_id": "jalagata-7ab7e",
    "storage_bucket": "jalagata-7ab7e.appspot.com"
  },
  "client": [
    {
      "client_info": {
        "mobilesdk_app_id": "1:936578715641:android:fb7ade750589458a777728",
        "android_client_info": {
          "package_name": "com.example.jalagata"
        }
      },
      "oauth_client": [],
      "api_key": [
        {
          "current_key": "AIzaSyCduAVpWij6NU0K6UG5WpFn0vtR9k4T_vo"
        }
      ],
      "services": {
        "appinvite_service": {
          "other_platform_oauth_client": []
        }
      }
    }
  ],
  "configuration_version": "1"
}